mopidy_mobile/__init__.py
mopidy_mobile/ext.conf
mopidy_mobile/web.py
mopidy_mobile/www/index.html
mopidy_mobile/www/manifest.json
mopidy_mobile/www/mopidy-mobile.bundle.min.js
mopidy_mobile/www/app/settings/coverartarchive.svg
mopidy_mobile/www/app/settings/icon.png
mopidy_mobile/www/app/settings/lastfm.gif
mopidy_mobile/www/app/settings/mopidy.png
mopidy_mobile/www/css/ionic-dark.min.css
mopidy_mobile/www/css/ionic-light.min.css
mopidy_mobile/www/css/ionic-sprites.png
mopidy_mobile/www/images/apple-touch-icon-120x120.png
mopidy_mobile/www/images/apple-touch-icon-152x152.png
mopidy_mobile/www/images/apple-touch-icon-180x180.png
mopidy_mobile/www/images/apple-touch-icon-76x76.png
mopidy_mobile/www/images/icon-144x144.png
mopidy_mobile/www/images/icon-192x192.png
mopidy_mobile/www/images/icon-72x72.png
mopidy_mobile/www/images/icon-96x96.png
mopidy_mobile/www/images/splash-320x480.png
mopidy_mobile/www/lib/ionic/fonts/ionicons.eot
mopidy_mobile/www/lib/ionic/fonts/ionicons.svg
mopidy_mobile/www/lib/ionic/fonts/ionicons.ttf
mopidy_mobile/www/lib/ionic/fonts/ionicons.woff
Mopidy_Mobile-1.11.0.dist-info/LICENSE
Mopidy_Mobile-1.11.0.dist-info/METADATA
Mopidy_Mobile-1.11.0.dist-info/WHEEL
Mopidy_Mobile-1.11.0.dist-info/entry_points.txt
Mopidy_Mobile-1.11.0.dist-info/top_level.txt
Mopidy_Mobile-1.11.0.dist-info/RECORD
