Metadata-Version: 2.1
Name: Mopidy-Mobile
Version: 1.11.0
Summary: Mopidy Web client extension for mobile devices
Home-page: https://github.com/tkem/mopidy-mobile
Author: Thomas Kemmer
Author-email: tkemmer@computer.org
License: Apache License, Version 2.0
Classifier: Environment :: Web Environment
Classifier: Intended Audience :: End Users/Desktop
Classifier: License :: OSI Approved :: Apache Software License
Classifier: Operating System :: OS Independent
Classifier: Programming Language :: Python :: 2
Classifier: Programming Language :: Python :: 2.7
Classifier: Programming Language :: Python :: 3
Classifier: Programming Language :: Python :: 3.7
Classifier: Programming Language :: Python :: 3.8
Classifier: Programming Language :: Python :: 3.9
Classifier: Topic :: Multimedia :: Sound/Audio :: Players
License-File: LICENSE
Requires-Dist: Mopidy >=0.19
Requires-Dist: setuptools
